jsondecoder.py
jsontest.py
JsonDecoderUtility-0.0.4.dist-info/METADATA
JsonDecoderUtility-0.0.4.dist-info/WHEEL
JsonDecoderUtility-0.0.4.dist-info/top_level.txt
JsonDecoderUtility-0.0.4.dist-info/RECORD
