Metadata-Version: 2.1
Name: JsonDecoderUtility
Version: 0.0.4
Summary: Json Decoder from URL
Home-page: UNKNOWN
Author: Bhasin Naik
Author-email: bhasinnaik@gmail.com
License: UNKNOWN
Platform: UNKNOWN
Classifier: Programming Language :: Python :: 3
Classifier: Programming Language :: Python :: 3.6
Classifier: Programming Language :: Python :: 3.7
Classifier: Programming Language :: Python :: 3.8
Classifier: License :: OSI Approved :: GNU General Public License v3 or later (GPLv3+)
Classifier: Operating System :: OS Independent
